pbga/__init__.py
pbga/base.py
pbga/database.py
pbga/effects.py
pbga/utils.py
pbga/jar/h2-1.4.199.jar
pbga-0.0.6.dist-info/LICENSE
pbga-0.0.6.dist-info/METADATA
pbga-0.0.6.dist-info/WHEEL
pbga-0.0.6.dist-info/top_level.txt
pbga-0.0.6.dist-info/RECORD
