Metadata-Version: 2.1
Name: pbga
Version: 0.0.6
Summary: Library of Python utilities for PacBio Genomes Analysis
Home-page: https://github.com/TheJacksonLaboratory/PBGA-python-toolkit
Author: Daniel Danis
Author-email: daniel.gordon.danis@gmail.com
License: GPLv3
Keywords: bioinformatics genomics
Platform: UNKNOWN
Requires-Dist: psycopg2-binary (>=2.8.3)
